{
	"song": {
		"sectionLengths": [],
		"player1": "bf",
		"player2": "gf",
		"notes": [
			{
				"sectionNotes": [],
				"lengthInSteps": 16,
				"typeOfSection": 0,
				"mustHitSection": false
			},
			{
				"sectionNotes": [],
				"lengthInSteps": 16,
				"typeOfSection": 0,
				"mustHitSection": true
			},
			{
				"sectionNotes": [],
				"lengthInSteps": 16,
				"typeOfSection": 0,
				"mustHitSection": false
			},
			{
				"sectionNotes": [],
				"lengthInSteps": 16,
				"typeOfSection": 0,
				"mustHitSection": true
			},
			{
				"sectionNotes": [
					[
						7384.61538461538,
						0,
						0
					],
					[
						7500,
						1,
						0
					]
				],
				"lengthInSteps": 16,
				"typeOfSection": 0,
				"mustHitSection": false
			},
			{
				"sectionNotes": [
					[
						9230.76923076923,
						3,
						0
					],
					[
						9346.15384615385,
						2,
						0
					]
				],
				"lengthInSteps": 16,
				"typeOfSection": 0,
				"mustHitSection": false
			},
			{
				"sectionNotes": [
					[
						11076.9230769231,
						0,
						0
					],
					[
						11192.3076923077,
						1,
						0
					]
				],
				"lengthInSteps": 16,
				"typeOfSection": 0,
				"mustHitSection": false
			},
			{
				"sectionNotes": [
					[
						12923.0769230769,
						3,
						0
					],
					[
						13038.4615384615,
						2,
						0
					]
				],
				"lengthInSteps": 16,
				"typeOfSection": 0,
				"mustHitSection": false
			},
			{
				"sectionNotes": [
					[
						14769.2307692308,
						0,
						0
					],
					[
						14884.6153846154,
						1,
						0
					]
				],
				"lengthInSteps": 16,
				"typeOfSection": 0,
				"mustHitSection": true
			},
			{
				"sectionNotes": [
					[
						16615.3846153846,
						3,
						0
					],
					[
						16730.7692307692,
						2,
						0
					]
				],
				"lengthInSteps": 16,
				"typeOfSection": 0,
				"mustHitSection": true
			},
			{
				"sectionNotes": [
					[
						18461.5384615385,
						0,
						0
					],
					[
						18576.9230769231,
						1,
						0
					]
				],
				"lengthInSteps": 16,
				"typeOfSection": 0,
				"mustHitSection": true
			},
			{
				"sectionNotes": [
					[
						20307.6923076923,
						3,
						0
					],
					[
						20423.0769230769,
						2,
						0
					]
				],
				"lengthInSteps": 16,
				"typeOfSection": 0,
				"mustHitSection": true
			},
			{
				"sectionNotes": [
					[
						22153.8461538462,
						2,
						0
					],
					[
						22269.2307692308,
						3,
						0
					],
					[
						22384.6153846154,
						2,
						0
					]
				],
				"lengthInSteps": 16,
				"typeOfSection": 0,
				"mustHitSection": false
			},
			{
				"sectionNotes": [
					[
						24000,
						1,
						0
					],
					[
						24115.3846153846,
						0,
						0
					],
					[
						24230.7692307692,
						1,
						0
					]
				],
				"lengthInSteps": 16,
				"typeOfSection": 0,
				"mustHitSection": false
			},
			{
				"sectionNotes": [
					[
						25846.1538461539,
						2,
						0
					],
					[
						25961.5384615385,
						3,
						0
					],
					[
						26076.9230769231,
						2,
						0
					]
				],
				"lengthInSteps": 16,
				"typeOfSection": 0,
				"mustHitSection": false
			},
			{
				"sectionNotes": [
					[
						27692.3076923077,
						1,
						0
					],
					[
						27807.6923076923,
						0,
						0
					],
					[
						27923.0769230769,
						1,
						0
					]
				],
				"lengthInSteps": 16,
				"typeOfSection": 0,
				"mustHitSection": false
			},
			{
				"sectionNotes": [
					[
						29538.4615384615,
						2,
						0
					],
					[
						29653.8461538462,
						3,
						0
					],
					[
						29769.2307692308,
						2,
						0
					]
				],
				"lengthInSteps": 16,
				"typeOfSection": 0,
				"mustHitSection": true
			},
			{
				"sectionNotes": [
					[
						31384.6153846154,
						1,
						0
					],
					[
						31500,
						0,
						0
					],
					[
						31615.3846153846,
						1,
						0
					]
				],
				"lengthInSteps": 16,
				"typeOfSection": 0,
				"mustHitSection": true
			},
			{
				"sectionNotes": [
					[
						33230.7692307692,
						2,
						0
					],
					[
						33346.1538461539,
						3,
						0
					],
					[
						33461.5384615385,
						2,
						0
					]
				],
				"lengthInSteps": 16,
				"typeOfSection": 0,
				"mustHitSection": true
			},
			{
				"sectionNotes": [
					[
						35076.9230769231,
						1,
						0
					],
					[
						35192.3076923077,
						0,
						0
					],
					[
						35307.6923076923,
						1,
						0
					]
				],
				"lengthInSteps": 16,
				"typeOfSection": 0,
				"mustHitSection": true
			},
			{
				"sectionNotes": [
					[
						36923.0769230769,
						1,
						0
					],
					[
						37038.4615384615,
						0,
						0
					],
					[
						37153.8461538462,
						1,
						0
					],
					[
						37269.2307692308,
						0,
						0
					],
					[
						37384.6153846154,
						1,
						0
					],
					[
						37500,
						2,
						0
					],
					[
						37615.3846153846,
						3,
						0
					],
					[
						37730.7692307692,
						2,
						0
					],
					[
						37846.1538461539,
						1,
						0
					],
					[
						37961.5384615385,
						0,
						0
					],
					[
						38076.9230769231,
						1,
						0
					],
					[
						38192.3076923077,
						2,
						0
					],
					[
						38307.6923076923,
						1,
						0
					],
					[
						38423.0769230769,
						0,
						0
					],
					[
						38538.4615384615,
						1,
						0
					],
					[
						38653.8461538462,
						2,
						0
					],
					[
						37153.8461538462,
						3,
						0
					],
					[
						37615.3846153846,
						0,
						0
					],
					[
						37961.5384615385,
						2,
						0
					],
					[
						38307.6923076923,
						3,
						0
					],
					[
						38423.0769230769,
						2,
						0
					]
				],
				"lengthInSteps": 16,
				"typeOfSection": 0,
				"mustHitSection": false
			},
			{
				"sectionNotes": [
					[
						38769.2307692307,
						1,
						0
					],
					[
						38884.6153846153,
						0,
						0
					],
					[
						39000,
						1,
						0
					],
					[
						39115.3846153846,
						0,
						0
					],
					[
						39230.7692307692,
						1,
						0
					],
					[
						39346.1538461538,
						2,
						0
					],
					[
						39461.5384615384,
						3,
						0
					],
					[
						39576.923076923,
						2,
						0
					],
					[
						39692.3076923077,
						1,
						0
					],
					[
						39807.6923076923,
						0,
						0
					],
					[
						39923.0769230769,
						1,
						0
					],
					[
						40038.4615384615,
						2,
						0
					],
					[
						40153.8461538461,
						1,
						0
					],
					[
						40269.2307692307,
						0,
						0
					],
					[
						40384.6153846153,
						1,
						0
					],
					[
						40500,
						2,
						0
					],
					[
						39000,
						3,
						0
					],
					[
						39461.5384615385,
						0,
						0
					],
					[
						39807.6923076923,
						2,
						0
					],
					[
						40153.8461538462,
						3,
						0
					],
					[
						40269.2307692308,
						2,
						0
					]
				],
				"lengthInSteps": 16,
				"typeOfSection": 0,
				"mustHitSection": false
			},
			{
				"sectionNotes": [
					[
						40615.3846153846,
						1,
						0
					],
					[
						40730.7692307692,
						0,
						0
					],
					[
						40846.1538461539,
						1,
						0
					],
					[
						40961.5384615385,
						2,
						0
					],
					[
						41076.9230769231,
						3,
						0
					],
					[
						41192.3076923077,
						2,
						0
					],
					[
						41307.6923076923,
						1,
						0
					],
					[
						41423.0769230769,
						2,
						0
					],
					[
						41538.4615384615,
						3,
						0
					],
					[
						41653.8461538462,
						2,
						0
					],
					[
						41769.2307692308,
						3,
						0
					],
					[
						41884.6153846154,
						2,
						0
					],
					[
						42000,
						1,
						0
					],
					[
						42115.3846153846,
						0,
						0
					],
					[
						42230.7692307692,
						1,
						0
					],
					[
						42346.1538461539,
						0,
						0
					],
					[
						41076.9230769231,
						1,
						0
					],
					[
						41538.4615384615,
						1,
						0
					],
					[
						42000,
						2,
						0
					],
					[
						42230.7692307692,
						3,
						0
					],
					[
						41307.6923076923,
						3,
						0
					],
					[
						40730.7692307692,
						3,
						0
					]
				],
				"lengthInSteps": 16,
				"typeOfSection": 0,
				"mustHitSection": false
			},
			{
				"sectionNotes": [
					[
						42461.5384615385,
						1,
						0
					],
					[
						42576.9230769231,
						2,
						0
					],
					[
						42692.3076923077,
						3,
						0
					],
					[
						42807.6923076923,
						2,
						0
					],
					[
						42923.0769230769,
						1,
						0
					],
					[
						43038.4615384615,
						2,
						0
					],
					[
						43153.8461538462,
						3,
						0
					],
					[
						43269.2307692308,
						2,
						0
					],
					[
						43384.6153846154,
						1,
						0
					],
					[
						43500,
						0,
						0
					],
					[
						43615.3846153846,
						1,
						0
					],
					[
						43730.7692307692,
						2,
						0
					],
					[
						43846.1538461538,
						3,
						0
					],
					[
						43961.5384615385,
						2,
						0
					],
					[
						44076.9230769231,
						1,
						0
					],
					[
						44192.3076923077,
						0,
						0
					],
					[
						42692.3076923077,
						1,
						0
					],
					[
						42923.0769230769,
						3,
						0
					],
					[
						43153.8461538462,
						1,
						0
					],
					[
						43384.6153846154,
						3,
						0
					],
					[
						43500,
						2,
						0
					],
					[
						43730.7692307692,
						3,
						0
					],
					[
						43730.7692307692,
						1,
						0
					],
					[
						43961.5384615385,
						0,
						0
					],
					[
						44192.3076923077,
						3,
						0
					]
				],
				"lengthInSteps": 16,
				"typeOfSection": 0,
				"mustHitSection": false
			},
			{
				"sectionNotes": [
					[
						44307.6923076923,
						1,
						0
					],
					[
						44423.0769230769,
						0,
						0
					],
					[
						44538.4615384616,
						1,
						0
					],
					[
						44653.8461538462,
						0,
						0
					],
					[
						44769.2307692308,
						1,
						0
					],
					[
						44884.6153846154,
						2,
						0
					],
					[
						45000,
						3,
						0
					],
					[
						45115.3846153846,
						2,
						0
					],
					[
						45230.7692307693,
						1,
						0
					],
					[
						45346.1538461539,
						0,
						0
					],
					[
						45461.5384615385,
						1,
						0
					],
					[
						45576.9230769231,
						2,
						0
					],
					[
						45692.3076923077,
						1,
						0
					],
					[
						45807.6923076923,
						0,
						0
					],
					[
						45923.0769230769,
						1,
						0
					],
					[
						46038.4615384616,
						2,
						0
					],
					[
						44538.4615384615,
						3,
						0
					],
					[
						45000,
						0,
						0
					],
					[
						45346.1538461539,
						2,
						0
					],
					[
						45692.3076923077,
						3,
						0
					],
					[
						45807.6923076923,
						2,
						0
					]
				],
				"lengthInSteps": 16,
				"typeOfSection": 0,
				"mustHitSection": true
			},
			{
				"sectionNotes": [
					[
						46153.8461538461,
						1,
						0
					],
					[
						46269.2307692307,
						0,
						0
					],
					[
						46384.6153846154,
						1,
						0
					],
					[
						46500,
						0,
						0
					],
					[
						46615.3846153846,
						1,
						0
					],
					[
						46730.7692307692,
						2,
						0
					],
					[
						46846.1538461538,
						3,
						0
					],
					[
						46961.5384615384,
						2,
						0
					],
					[
						47076.9230769231,
						1,
						0
					],
					[
						47192.3076923077,
						0,
						0
					],
					[
						47307.6923076923,
						1,
						0
					],
					[
						47423.0769230769,
						2,
						0
					],
					[
						47538.4615384615,
						1,
						0
					],
					[
						47653.8461538461,
						0,
						0
					],
					[
						47769.2307692307,
						1,
						0
					],
					[
						47884.6153846154,
						2,
						0
					],
					[
						46384.6153846154,
						3,
						0
					],
					[
						46846.1538461539,
						0,
						0
					],
					[
						47192.3076923077,
						2,
						0
					],
					[
						47538.4615384615,
						3,
						0
					],
					[
						47653.8461538462,
						2,
						0
					]
				],
				"lengthInSteps": 16,
				"typeOfSection": 0,
				"mustHitSection": true
			},
			{
				"sectionNotes": [
					[
						48000,
						1,
						0
					],
					[
						48115.3846153846,
						0,
						0
					],
					[
						48230.7692307693,
						1,
						0
					],
					[
						48346.1538461539,
						2,
						0
					],
					[
						48461.5384615385,
						3,
						0
					],
					[
						48576.9230769231,
						2,
						0
					],
					[
						48692.3076923077,
						1,
						0
					],
					[
						48807.6923076923,
						2,
						0
					],
					[
						48923.0769230769,
						3,
						0
					],
					[
						49038.4615384616,
						2,
						0
					],
					[
						49153.8461538462,
						3,
						0
					],
					[
						49269.2307692308,
						2,
						0
					],
					[
						49384.6153846154,
						1,
						0
					],
					[
						49500,
						0,
						0
					],
					[
						49615.3846153846,
						1,
						0
					],
					[
						49730.7692307693,
						0,
						0
					],
					[
						48461.5384615385,
						1,
						0
					],
					[
						48923.0769230769,
						1,
						0
					],
					[
						49384.6153846154,
						2,
						0
					],
					[
						49615.3846153846,
						3,
						0
					],
					[
						48692.3076923077,
						3,
						0
					],
					[
						48115.3846153846,
						3,
						0
					]
				],
				"lengthInSteps": 16,
				"typeOfSection": 0,
				"mustHitSection": true
			},
			{
				"typeOfSection": 0,
				"sectionNotes": [
					[
						49846.1538461538,
						1,
						0
					],
					[
						49961.5384615384,
						0,
						0
					],
					[
						50076.9230769231,
						1,
						0
					],
					[
						50192.3076923077,
						2,
						0
					],
					[
						50307.6923076923,
						3,
						0
					],
					[
						50423.0769230769,
						2,
						0
					],
					[
						50538.4615384615,
						1,
						0
					],
					[
						50653.8461538461,
						2,
						0
					],
					[
						50769.2307692307,
						3,
						0
					],
					[
						50884.6153846154,
						2,
						0
					],
					[
						51000,
						3,
						0
					],
					[
						51115.3846153846,
						2,
						0
					],
					[
						51230.7692307692,
						1,
						0
					],
					[
						51346.1538461538,
						0,
						0
					],
					[
						51461.5384615384,
						1,
						0
					],
					[
						51576.9230769231,
						0,
						0
					],
					[
						50307.6923076923,
						1,
						0
					],
					[
						50769.2307692308,
						1,
						0
					],
					[
						51230.7692307692,
						2,
						0
					],
					[
						51461.5384615385,
						3,
						0
					],
					[
						50538.4615384615,
						3,
						0
					],
					[
						49961.5384615385,
						3,
						0
					]
				],
				"lengthInSteps": 16,
				"bpm": 100,
				"changeBPM": false,
				"mustHitSection": true
			},
			{
				"lengthInSteps": 16,
				"typeOfSection": 0,
				"sectionNotes": [
					[
						51692.3076923077,
						2,
						403.846153846154
					],
					[
						52269.2307692308,
						3,
						115.384615384615
					],
					[
						52456.7307692308,
						2,
						0
					],
					[
						52549.0384615384,
						1,
						0
					],
					[
						52681.7307692308,
						0,
						403.846153846154
					],
					[
						53160.5769230769,
						1,
						288.461538461538
					]
				],
				"altAnim": false,
				"bpm": 100,
				"changeBPM": false,
				"mustHitSection": true
			},
			{
				"lengthInSteps": 16,
				"typeOfSection": 0,
				"sectionNotes": [
					[
						53538.4615384615,
						2,
						0
					],
					[
						53653.8461538461,
						3,
						0
					],
					[
						53769.2307692308,
						0,
						807.692307692308
					],
					[
						54692.3076923077,
						1,
						576.923076923077
					]
				],
				"altAnim": false,
				"bpm": 108,
				"changeBPM": false,
				"mustHitSection": true
			},
			{
				"lengthInSteps": 16,
				"typeOfSection": 0,
				"sectionNotes": [
					[
						55384.6153846154,
						2,
						230.769230769231
					],
					[
						55699.0384615384,
						3,
						173.076923076923
					],
					[
						55958.6538461538,
						2,
						173.076923076923
					],
					[
						56270.1923076923,
						3,
						0
					],
					[
						56350.9615384615,
						2,
						0
					],
					[
						56884.6153846154,
						0,
						0
					],
					[
						57115.3846153846,
						0,
						0
					],
					[
						56538.4615384615,
						1,
						0
					]
				],
				"altAnim": false,
				"bpm": 112,
				"changeBPM": false,
				"mustHitSection": true
			},
			{
				"lengthInSteps": 16,
				"typeOfSection": 0,
				"sectionNotes": [
					[
						57230.7692307692,
						1,
						0
					],
					[
						57346.1538461538,
						2,
						0
					],
					[
						57461.5384615384,
						3,
						0
					],
					[
						57576.9230769231,
						2,
						0
					],
					[
						57767.3076923077,
						1,
						0
					],
					[
						57923.0769230769,
						0,
						0
					],
					[
						58116.3461538461,
						1,
						0
					],
					[
						58269.2307692308,
						2,
						0
					],
					[
						58468.2692307692,
						3,
						0
					],
					[
						58650,
						2,
						0
					],
					[
						58846.1538461538,
						1,
						0
					]
				],
				"altAnim": false,
				"bpm": 115,
				"changeBPM": false,
				"mustHitSection": true
			},
			{
				"lengthInSteps": 16,
				"typeOfSection": 0,
				"sectionNotes": [
					[
						59076.9230769231,
						0,
						3576.92307692307
					]
				],
				"altAnim": false,
				"bpm": 119,
				"changeBPM": false,
				"mustHitSection": true
			},
			{
				"lengthInSteps": 16,
				"typeOfSection": 0,
				"sectionNotes": [],
				"altAnim": false,
				"bpm": 123,
				"changeBPM": false,
				"mustHitSection": true
			},
			{
				"lengthInSteps": 16,
				"typeOfSection": 0,
				"sectionNotes": [],
				"altAnim": false,
				"bpm": 126,
				"changeBPM": false,
				"mustHitSection": true
			},
			{
				"lengthInSteps": 16,
				"typeOfSection": 0,
				"sectionNotes": [
					[
						64615.3846153846,
						0,
						0
					],
					[
						64673.0769230769,
						1,
						0
					],
					[
						64730.7692307692,
						2,
						0
					],
					[
						64788.4615384615,
						3,
						0
					],
					[
						64846.1538461538,
						0,
						0
					],
					[
						64903.8461538461,
						1,
						0
					],
					[
						64961.5384615384,
						2,
						0
					],
					[
						65019.2307692307,
						3,
						0
					],
					[
						65076.923076923,
						0,
						0
					],
					[
						65134.6153846154,
						1,
						0
					],
					[
						65192.3076923077,
						2,
						0
					],
					[
						65250,
						3,
						0
					],
					[
						65307.6923076923,
						0,
						0
					],
					[
						65365.3846153846,
						1,
						0
					],
					[
						65423.0769230769,
						2,
						0
					],
					[
						65480.7692307692,
						3,
						0
					],
					[
						65538.4615384615,
						0,
						0
					],
					[
						65596.1538461538,
						1,
						0
					],
					[
						65653.8461538461,
						3,
						0
					],
					[
						65711.5384615384,
						2,
						0
					],
					[
						65769.2307692307,
						0,
						0
					],
					[
						65826.923076923,
						1,
						0
					],
					[
						65884.6153846154,
						3,
						0
					],
					[
						65942.3076923077,
						2,
						0
					],
					[
						66000,
						0,
						0
					],
					[
						66057.6923076923,
						1,
						0
					],
					[
						66115.3846153846,
						3,
						0
					],
					[
						66173.0769230769,
						2,
						0
					],
					[
						66230.7692307692,
						0,
						0
					],
					[
						66288.4615384615,
						1,
						0
					],
					[
						66346.1538461538,
						3,
						0
					],
					[
						66403.8461538461,
						2,
						0
					]
				],
				"altAnim": false,
				"bpm": 130,
				"changeBPM": false,
				"mustHitSection": true
			},
			{
				"lengthInSteps": 16,
				"typeOfSection": 0,
				"sectionNotes": [
					[
						66461.5384615384,
						0,
						0
					],
					[
						66519.2307692307,
						1,
						0
					],
					[
						66576.923076923,
						2,
						0
					],
					[
						66634.6153846154,
						3,
						0
					],
					[
						66692.3076923077,
						0,
						0
					],
					[
						66750,
						1,
						0
					],
					[
						66807.6923076923,
						2,
						0
					],
					[
						66865.3846153846,
						3,
						0
					],
					[
						66923.0769230769,
						0,
						0
					],
					[
						66980.7692307692,
						1,
						0
					],
					[
						67038.4615384615,
						2,
						0
					],
					[
						67096.1538461538,
						3,
						0
					],
					[
						67153.8461538461,
						0,
						0
					],
					[
						67211.5384615384,
						1,
						0
					],
					[
						67269.2307692307,
						2,
						0
					],
					[
						67326.923076923,
						3,
						0
					],
					[
						67384.6153846154,
						0,
						0
					],
					[
						67442.3076923077,
						1,
						0
					],
					[
						67500,
						3,
						0
					],
					[
						67557.6923076923,
						2,
						0
					],
					[
						67615.3846153846,
						0,
						0
					],
					[
						67673.0769230769,
						1,
						0
					],
					[
						67730.7692307692,
						3,
						0
					],
					[
						67788.4615384615,
						2,
						0
					],
					[
						67846.1538461538,
						0,
						0
					],
					[
						67903.8461538461,
						1,
						0
					],
					[
						67961.5384615384,
						3,
						0
					],
					[
						68019.2307692307,
						2,
						0
					],
					[
						68076.923076923,
						0,
						0
					],
					[
						68134.6153846154,
						1,
						0
					],
					[
						68192.3076923077,
						3,
						0
					],
					[
						68250,
						2,
						0
					]
				],
				"altAnim": false,
				"bpm": 134,
				"changeBPM": false,
				"mustHitSection": false
			},
			{
				"lengthInSteps": 16,
				"typeOfSection": 0,
				"sectionNotes": [
					[
						68307.6923076923,
						0,
						0
					],
					[
						68365.3846153846,
						1,
						0
					],
					[
						68423.0769230769,
						2,
						0
					],
					[
						68480.7692307692,
						3,
						0
					],
					[
						68538.4615384615,
						0,
						0
					],
					[
						68596.1538461538,
						1,
						0
					],
					[
						68653.8461538461,
						2,
						0
					],
					[
						68711.5384615384,
						3,
						0
					],
					[
						68769.2307692307,
						0,
						0
					],
					[
						68826.923076923,
						1,
						0
					],
					[
						68884.6153846154,
						2,
						0
					],
					[
						68942.3076923077,
						3,
						0
					],
					[
						69000,
						0,
						0
					],
					[
						69057.6923076923,
						1,
						0
					],
					[
						69115.3846153846,
						2,
						0
					],
					[
						69173.0769230769,
						3,
						0
					],
					[
						69230.7692307692,
						0,
						0
					],
					[
						69288.4615384615,
						1,
						0
					],
					[
						69346.1538461538,
						3,
						0
					],
					[
						69403.8461538461,
						2,
						0
					],
					[
						69461.5384615384,
						0,
						0
					],
					[
						69519.2307692307,
						1,
						0
					],
					[
						69576.923076923,
						3,
						0
					],
					[
						69634.6153846153,
						2,
						0
					],
					[
						69692.3076923077,
						0,
						0
					],
					[
						69750,
						1,
						0
					],
					[
						69807.6923076923,
						3,
						0
					],
					[
						69865.3846153846,
						2,
						0
					],
					[
						69923.0769230769,
						0,
						0
					],
					[
						69980.7692307692,
						1,
						0
					],
					[
						70038.4615384615,
						3,
						0
					],
					[
						70096.1538461538,
						2,
						0
					]
				],
				"altAnim": false,
				"bpm": 138,
				"changeBPM": false,
				"mustHitSection": true
			},
			{
				"lengthInSteps": 16,
				"typeOfSection": 0,
				"sectionNotes": [
					[
						70153.8461538461,
						0,
						0
					],
					[
						70211.5384615384,
						1,
						0
					],
					[
						70269.2307692307,
						2,
						0
					],
					[
						70326.923076923,
						3,
						0
					],
					[
						70384.6153846154,
						0,
						0
					],
					[
						70442.3076923077,
						1,
						0
					],
					[
						70500,
						2,
						0
					],
					[
						70557.6923076923,
						3,
						0
					],
					[
						70615.3846153846,
						0,
						0
					],
					[
						70673.0769230769,
						1,
						0
					],
					[
						70730.7692307692,
						2,
						0
					],
					[
						70788.4615384615,
						3,
						0
					],
					[
						70846.1538461538,
						0,
						0
					],
					[
						70903.8461538461,
						1,
						0
					],
					[
						70961.5384615384,
						2,
						0
					],
					[
						71019.2307692307,
						3,
						0
					],
					[
						71076.923076923,
						0,
						0
					],
					[
						71134.6153846153,
						1,
						0
					],
					[
						71192.3076923077,
						3,
						0
					],
					[
						71250,
						2,
						0
					],
					[
						71307.6923076923,
						0,
						0
					],
					[
						71365.3846153846,
						1,
						0
					],
					[
						71423.0769230769,
						3,
						0
					],
					[
						71480.7692307692,
						2,
						0
					],
					[
						71538.4615384615,
						0,
						0
					],
					[
						71596.1538461538,
						1,
						0
					],
					[
						71653.8461538461,
						3,
						0
					],
					[
						71711.5384615384,
						2,
						0
					],
					[
						71769.2307692307,
						0,
						0
					],
					[
						71826.923076923,
						1,
						0
					],
					[
						71884.6153846153,
						3,
						0
					],
					[
						71942.3076923077,
						2,
						0
					]
				],
				"altAnim": false,
				"bpm": 141,
				"changeBPM": false,
				"mustHitSection": false
			},
			{
				"lengthInSteps": 16,
				"typeOfSection": 0,
				"sectionNotes": [
					[
						72000,
						0,
						0
					],
					[
						72057.6923076923,
						1,
						0
					],
					[
						72115.3846153846,
						2,
						0
					],
					[
						72173.0769230769,
						3,
						0
					],
					[
						72230.7692307692,
						0,
						0
					],
					[
						72288.4615384615,
						1,
						0
					],
					[
						72346.1538461538,
						2,
						0
					],
					[
						72403.8461538461,
						3,
						0
					],
					[
						72461.5384615384,
						0,
						0
					],
					[
						72519.2307692307,
						1,
						0
					],
					[
						72576.923076923,
						2,
						0
					],
					[
						72634.6153846153,
						3,
						0
					],
					[
						72692.3076923077,
						0,
						0
					],
					[
						72750,
						1,
						0
					],
					[
						72807.6923076923,
						2,
						0
					],
					[
						72865.3846153846,
						3,
						0
					],
					[
						72923.0769230769,
						0,
						0
					],
					[
						72980.7692307692,
						1,
						0
					],
					[
						73038.4615384615,
						3,
						0
					],
					[
						73096.1538461538,
						2,
						0
					],
					[
						73153.8461538461,
						0,
						0
					],
					[
						73211.5384615384,
						1,
						0
					],
					[
						73269.2307692307,
						3,
						0
					],
					[
						73326.923076923,
						2,
						0
					],
					[
						73384.6153846153,
						0,
						0
					],
					[
						73442.3076923077,
						1,
						0
					],
					[
						73500,
						3,
						0
					],
					[
						73557.6923076923,
						2,
						0
					],
					[
						73615.3846153846,
						0,
						0
					],
					[
						73673.0769230769,
						1,
						0
					],
					[
						73730.7692307692,
						3,
						0
					],
					[
						73788.4615384615,
						2,
						0
					]
				],
				"altAnim": false,
				"bpm": 145,
				"changeBPM": false,
				"mustHitSection": true
			},
			{
				"lengthInSteps": 16,
				"typeOfSection": 0,
				"sectionNotes": [],
				"altAnim": false,
				"bpm": 149,
				"changeBPM": false,
				"mustHitSection": true
			},
			{
				"lengthInSteps": 16,
				"typeOfSection": 0,
				"sectionNotes": [],
				"altAnim": false,
				"bpm": 150,
				"changeBPM": false,
				"mustHitSection": true
			},
			{
				"sectionNotes": [],
				"typeOfSection": 0,
				"lengthInSteps": 16,
				"altAnim": false,
				"mustHitSection": true,
				"changeBPM": false,
				"bpm": 150
			},
			{
				"sectionNotes": [],
				"typeOfSection": 0,
				"lengthInSteps": 16,
				"altAnim": false,
				"mustHitSection": true,
				"changeBPM": false,
				"bpm": 150
			},
			{
				"sectionNotes": [],
				"typeOfSection": 0,
				"lengthInSteps": 16,
				"altAnim": false,
				"mustHitSection": true,
				"changeBPM": false,
				"bpm": 150
			},
			{
				"lengthInSteps": 16,
				"typeOfSection": 0,
				"sectionNotes": [],
				"altAnim": false,
				"bpm": 150,
				"changeBPM": false,
				"mustHitSection": true
			},
			{
				"sectionNotes": [],
				"typeOfSection": 0,
				"lengthInSteps": 16,
				"altAnim": false,
				"mustHitSection": true,
				"changeBPM": false,
				"bpm": 150
			},
			{
				"sectionNotes": [],
				"typeOfSection": 0,
				"lengthInSteps": 16,
				"altAnim": false,
				"mustHitSection": true,
				"changeBPM": false,
				"bpm": 150
			},
			{
				"sectionNotes": [],
				"typeOfSection": 0,
				"lengthInSteps": 16,
				"altAnim": false,
				"mustHitSection": true,
				"changeBPM": false,
				"bpm": 150
			},
			{
				"lengthInSteps": 16,
				"typeOfSection": 0,
				"sectionNotes": [],
				"altAnim": false,
				"bpm": 150,
				"changeBPM": false,
				"mustHitSection": true
			},
			{
				"lengthInSteps": 16,
				"typeOfSection": 0,
				"sectionNotes": [],
				"altAnim": false,
				"bpm": 199,
				"changeBPM": false,
				"mustHitSection": true
			},
			{
				"lengthInSteps": 16,
				"typeOfSection": 0,
				"sectionNotes": [],
				"altAnim": false,
				"bpm": 199,
				"changeBPM": false,
				"mustHitSection": true
			},
			{
				"lengthInSteps": 16,
				"typeOfSection": 0,
				"sectionNotes": [
					[
						62713.5678391959,
						-1,
						"Play Animation",
						"heh",
						"0"
					]
				],
				"altAnim": false,
				"bpm": 199,
				"changeBPM": false,
				"mustHitSection": true
			},
			{
				"lengthInSteps": 16,
				"typeOfSection": 0,
				"sectionNotes": [],
				"altAnim": false,
				"bpm": 199,
				"changeBPM": false,
				"mustHitSection": true
			},
			{
				"lengthInSteps": 16,
				"typeOfSection": 0,
				"sectionNotes": [],
				"altAnim": false,
				"bpm": 199,
				"changeBPM": false,
				"mustHitSection": true
			},
			{
				"lengthInSteps": 16,
				"typeOfSection": 0,
				"sectionNotes": [],
				"altAnim": false,
				"bpm": 199,
				"changeBPM": false,
				"mustHitSection": true
			},
			{
				"lengthInSteps": 16,
				"typeOfSection": 0,
				"sectionNotes": [],
				"altAnim": false,
				"bpm": 199,
				"changeBPM": false,
				"mustHitSection": true
			},
			{
				"lengthInSteps": 16,
				"typeOfSection": 0,
				"sectionNotes": [],
				"altAnim": false,
				"bpm": 199,
				"changeBPM": false,
				"mustHitSection": true
			},
			{
				"lengthInSteps": 16,
				"typeOfSection": 0,
				"sectionNotes": [],
				"altAnim": false,
				"bpm": 199,
				"changeBPM": false,
				"mustHitSection": true
			},
			{
				"lengthInSteps": 16,
				"typeOfSection": 0,
				"sectionNotes": [],
				"altAnim": false,
				"bpm": 199,
				"changeBPM": false,
				"mustHitSection": true
			},
			{
				"lengthInSteps": 16,
				"typeOfSection": 0,
				"sectionNotes": [],
				"altAnim": false,
				"bpm": 199,
				"changeBPM": false,
				"mustHitSection": true
			},
			{
				"sectionNotes": [],
				"typeOfSection": 0,
				"lengthInSteps": 16,
				"altAnim": false,
				"mustHitSection": true,
				"changeBPM": false,
				"bpm": 199
			},
			{
				"sectionNotes": [],
				"typeOfSection": 0,
				"lengthInSteps": 16,
				"altAnim": false,
				"mustHitSection": true,
				"changeBPM": false,
				"bpm": 199
			},
			{
				"sectionNotes": [],
				"typeOfSection": 0,
				"lengthInSteps": 16,
				"altAnim": false,
				"mustHitSection": true,
				"changeBPM": false,
				"bpm": 199
			},
			{
				"lengthInSteps": 16,
				"typeOfSection": 0,
				"sectionNotes": [],
				"altAnim": false,
				"bpm": 199,
				"changeBPM": false,
				"mustHitSection": true
			},
			{
				"sectionNotes": [],
				"typeOfSection": 0,
				"lengthInSteps": 16,
				"altAnim": false,
				"mustHitSection": true,
				"changeBPM": false,
				"bpm": 130
			},
			{
				"sectionNotes": [],
				"typeOfSection": 0,
				"lengthInSteps": 16,
				"altAnim": false,
				"mustHitSection": true,
				"changeBPM": false,
				"bpm": 130
			},
			{
				"sectionNotes": [],
				"typeOfSection": 0,
				"lengthInSteps": 16,
				"altAnim": false,
				"mustHitSection": true,
				"changeBPM": false,
				"bpm": 130
			},
			{
				"lengthInSteps": 16,
				"altAnim": false,
				"typeOfSection": 0,
				"sectionNotes": [],
				"bpm": 130,
				"changeBPM": false,
				"mustHitSection": true
			}
		],
		"player3": "gf",
		"song": "binted",
		"sections": 0,
		"needsVoices": true,
		"validScore": true,
		"speed": 2,
		"bpm": 130
	}
}